molotov_tools/__init__.py
molotov_tools/basic.py
molotov_tools-0.0.1.dist-info/LICENSE
molotov_tools-0.0.1.dist-info/METADATA
molotov_tools-0.0.1.dist-info/WHEEL
molotov_tools-0.0.1.dist-info/top_level.txt
molotov_tools-0.0.1.dist-info/RECORD
