Metadata-Version: 2.1
Name: molotov-tools
Version: 0.0.1
Summary: Personal use package wich contains my usefull tools
Home-page: UNKNOWN
Author: FF Molotov
Author-email: felipefulan@usp.br
License: UNKNOWN
Platform: UNKNOWN
Classifier: Programming Language :: Python :: 3
Classifier: License :: OSI Approved :: MIT License
Classifier: Operating System :: OS Independent
Requires-Python: >=3.8
License-File: LICENSE
